multiplexer_4_1/multiplexer_4_1.v
module multiplexer_4_1(
	input a,
	input b,
	input c,
	input d,
	input [1:0] sel,
	output y
);
	assign y = (~sel[1] & ~sel[0] & a) | 
		   (~sel[1] & sel[0] & b) |
		   (sel[1] & ~sel[0] & c) | 
		   (sel[1] & sel[1] & d);
endmodule

multiplexer_4_1/multiplexer_4_1_tb.v
`timescale 1ns/100ps

module multiplexer_4_1_tb;

	reg a,b,c,d;
	reg [1:0] sel;
	wire y;

	multiplexer_4_1 u0_DUT(
		.a(a),
		.b(b),
		.c(c),
		.d(d),
		.sel(sel),
		.y(y)
	);

	initial begin
		
		$dumpfile("test_4_1_mux.vcd");
		$dumpvars(0, multiplexer_4_1_tb);

		a=1'b0; b=1'b0; c=1'b0; d=1'b0; sel=2'b00; 

		#5 a=1'b1;
		#5 a=1'b0; sel=2'b01; 
		#5 b=1'b1; 
		#5 b=1'b0; sel=2'b10;
		#5 c=1'b1; 
		#5 c=1'b0; sel=2'b11;
		#5 c=1'b1;

		#5 $finish;
	end

endmodule

multiplexer_4_1/test_4_1_mux.vcd
$date
	Wed Jun  3 14:13:43 2026
$end
$version
	Icarus Verilog
$end
$timescale
	100ps
$end
$scope module multiplexer_4_1_tb $end
$var wire 1 ! y $end
$var reg 1 " a $end
$var reg 1 # b $end
$var reg 1 $ c $end
$var reg 1 % d $end
$var reg 2 & sel [1:0] $end
$scope module u0_DUT $end
$var wire 1 " a $end
$var wire 1 # b $end
$var wire 1 $ c $end
$var wire 1 % d $end
$var wire 2 ' sel [1:0] $end
$var wire 1 ! y $end
$upscope $end
$upscope $end
$enddefinitions $end
$comment Show the parameter values. $end
$dumpall
$end
#0
$dumpvars
b0 '
b0 &
0%
0$
0#
0"
0!
$end
#50
1!
1"
#100
0!
b1 &
b1 '
0"
#150
1!
1#
#200
0!
b10 &
b10 '
0#
#250
1!
1$
#300
0!
b11 &
b11 '
0$
#350
1$
