one_bit_full_adder/one_bit_full_adder.v
module one_bit_full_adder(
	input a,
	input b,
	input cin,
	output sum,
	output cout
);
	assign sum = (a ^ b ^ cin);
	assign cout = (cin & (a|b)) | (~cin & (a & b));
endmodule

one_bit_full_adder/one_bit_full_adder_tb.v
`timescale 1ns/100ps

module one_bit_full_adder_tb;

	reg a, b, cin;
	wire sum, cout;

	one_bit_full_adder u0_DUT(
		.a(a),
		.b(b),
		.cin(cin),
		.sum(sum),
		.cout(cout)
	);

	// initialize inputs
	
	initial begin
		$dumpfile("test_one_bit_full_adder.vcd");
		$dumpvars(0,one_bit_full_adder_tb);

		a=1'b0; b=1'b0; cin=1'b0;

		#5 a=1'b1;
		#5 a=1'b0; b=1'b1;
		#5 b=1'b0; cin=1'b1;
		#5 a=1'b1; 
		#5 cin=1'b0; b=1'b1; 
		#5 cin=1'b1; a=1'b0;
		#5 a=1'b1;
		#5 $finish;
	end

endmodule

one_bit_full_adder/test_one_bit_full_adder.vcd
$date
	Wed Jun  3 15:49:52 2026
$end
$version
	Icarus Verilog
$end
$timescale
	100ps
$end
$scope module one_bit_full_adder_tb $end
$var wire 1 ! sum $end
$var wire 1 " cout $end
$var reg 1 # a $end
$var reg 1 $ b $end
$var reg 1 % cin $end
$scope module u0_DUT $end
$var wire 1 # a $end
$var wire 1 $ b $end
$var wire 1 % cin $end
$var wire 1 " cout $end
$var wire 1 ! sum $end
$upscope $end
$upscope $end
$enddefinitions $end
$comment Show the parameter values. $end
$dumpall
$end
#0
$dumpvars
0%
0$
0#
0"
0!
$end
#50
1!
1#
#100
1$
0#
#150
1%
0$
#200
1"
0!
1#
#250
0!
1$
0%
#300
0!
0#
1%
#350
1!
1#
