magnitude_comparator/magnitude_comparator.v
module magnitude_comparator(
	input [3:0] a,
	input [3:0] b,
	output eq,
	output gt,
	output lt
);	
	
	assign eq = 	~( a[0] ^ b[0] ) &
			~( a[1] ^ b[1] ) &
			~( a[2] ^ b[2] ) &
			~( a[3] ^ b[3] );

	assign gt = 	( a[3] & ~b[3] ) | 
			( ~(a[3] ^ b[3]) & a[2] & ~b[2] ) |
			( ~(a[2] ^ b[2]) & a[1] & ~b[1] ) |
			( ~(a[1] ^ b[1]) & a[0] & ~b[0] );
	
	assign lt = 	( b[3] & ~a[3] ) |
			( ~(b[3] ^ a[3] ) & b[2] & ~a[2]) |
			( ~(b[2] ^ a[2] ) & b[1] & ~a[1]) |
			( ~(b[1] ^ a[1] ) & b[0] & ~a[0]);
endmodule

magnitude_comparator/magnitude_comparator_tb.v
`timescale 1ns/100ps

module magnitude_comparator_tb;

	reg [3:0] a, b;
	wire eq, gt, lt;

	magnitude_comparator u0_DUT(
		.a(a),
		.b(b),
		.eq(eq),
		.gt(gt),
		.lt(lt)
	);	

	// initiailize inputs
	
	initial begin
		$dumpfile("test_magnitude_comparator.vcd");
		$dumpvars(0, magnitude_comparator_tb);

		// define test

		a=4'b0000; b=4'b0000; // eq == 0

	
		// equality tests 
		#5 a=4'b0001; // eq == 1 
		#5 a=4'b1010; b=4'b1110; // eq == 0
		#5 a=4'b1100; b=4'b1100; // eq == 1

		// greater than tests
		#5 a=4'b0000; b=4'b0000; // gt == 0
		#5 a=4'b1000; // gt = 1
		#5 b=4'b1000; // gt = 0
		#5 a=4'b0101; b=4'b1000; // gt = 0
		#5 a=4'b0101; b=4'b0011; // gt = 1

		// less than tests
		#5 a=4'b0000; b=4'b0000; // lt == 0
		#5 b=4'b0010; //lt = 1
		#5 a=4'b0100; // lt = 0 
		#5 b=4'b1000; // lt = 1


		#5 $finish;
	end


	

endmodule

magnitude_comparator/test_magnitude_comparator.vcd
$date
	Thu Jun  4 12:01:50 2026
$end
$version
	Icarus Verilog
$end
$timescale
	100ps
$end
$scope module magnitude_comparator_tb $end
$var wire 1 ! lt $end
$var wire 1 " gt $end
$var wire 1 # eq $end
$var reg 4 $ a [3:0] $end
$var reg 4 % b [3:0] $end
$scope module u0_DUT $end
$var wire 4 & a [3:0] $end
$var wire 4 ' b [3:0] $end
$var wire 1 # eq $end
$var wire 1 " gt $end
$var wire 1 ! lt $end
$upscope $end
$upscope $end
$enddefinitions $end
$comment Show the parameter values. $end
$dumpall
$end
#0
$dumpvars
b0 '
b0 &
b0 %
b0 $
1#
0"
0!
$end
#50
0#
1"
b1 $
b1 &
#100
1!
0"
b1110 %
b1110 '
b1010 $
b1010 &
#150
0!
1#
b1100 %
b1100 '
b1100 $
b1100 &
#200
b0 %
b0 '
b0 $
b0 &
#250
1"
0#
b1000 $
b1000 &
#300
0"
1#
b1000 %
b1000 '
#350
1!
0#
1"
b101 $
b101 &
#400
0!
1"
b11 %
b11 '
#450
1#
0"
b0 %
b0 '
b0 $
b0 &
#500
0#
1!
b10 %
b10 '
#550
0!
1"
b100 $
b100 &
#600
0"
1!
b1000 %
b1000 '
