8-bit-register/eight_bit_register.v
module dff(
    input d,
    input clk,
    input reset,
    output reg q
);
    always @(posedge clk) begin
        if (reset)
            q <= 1'b0;
        else
            q <= d;
    end
endmodule


module eight_bit_register(
    input [7:0] D,
    input load_enable,
    input reset,
    input clk,
    output [7:0] Q
);
    wire [7:0] next_D;

    assign next_D = load_enable ? D : Q;

    dff b0(.d(next_D[0]), .clk(clk), .reset(reset), .q(Q[0]));
    dff b1(.d(next_D[1]), .clk(clk), .reset(reset), .q(Q[1]));
    dff b2(.d(next_D[2]), .clk(clk), .reset(reset), .q(Q[2]));
    dff b3(.d(next_D[3]), .clk(clk), .reset(reset), .q(Q[3]));
    dff b4(.d(next_D[4]), .clk(clk), .reset(reset), .q(Q[4]));
    dff b5(.d(next_D[5]), .clk(clk), .reset(reset), .q(Q[5]));
    dff b6(.d(next_D[6]), .clk(clk), .reset(reset), .q(Q[6]));
    dff b7(.d(next_D[7]), .clk(clk), .reset(reset), .q(Q[7]));

endmodule

8-bit-register/eight_bit_register_tb.v
`timescale 1ns/100ps

module eight_bit_register_tb;

    reg [7:0] D;
    reg load_enable, reset, clk;
    wire [7:0] Q;

    eight_bit_register u0_DUT(
        .D(D),
        .load_enable(load_enable),
        .reset(reset),
        .clk(clk),
        .Q(Q)
    );

    // Clock generation: 10 ns period
    always begin
        #5 clk = ~clk;
    end

    initial begin
        $dumpfile("test_eight_bit_register.vcd");
        $dumpvars(0, eight_bit_register_tb);

        clk = 1'b0;
        D = 8'b00000000;
        load_enable = 1'b0;
        reset = 1'b1;

        // Hold reset for one clock edge
        #10;
        reset = 1'b0;

        // Load first value
        D = 8'b10001111;
        load_enable = 1'b1;
        #10;

        // Disable loading; Q should hold 10001111
        load_enable = 1'b0;
        D = 8'b11110000;
        #10;

        // Enable loading; Q should update to 11110000
        load_enable = 1'b1;
        #10;

        // Reset; Q should become 00000000
        reset = 1'b1;
        #10;

        reset = 1'b0;
        load_enable = 1'b0;
        D = 8'b10101010;
        #10;

        $finish;
    end

endmodule

8-bit-register/test_eight_bit_register.vcd
$date
	Fri Jun  5 19:07:20 2026
$end
$version
	Icarus Verilog
$end
$timescale
	100ps
$end
$scope module eight_bit_register_tb $end
$var wire 8 ! Q [7:0] $end
$var reg 8 " D [7:0] $end
$var reg 1 # clk $end
$var reg 1 $ load_enable $end
$var reg 1 % reset $end
$scope module u0_DUT $end
$var wire 8 & D [7:0] $end
$var wire 1 # clk $end
$var wire 1 $ load_enable $end
$var wire 1 % reset $end
$var wire 8 ' next_D [7:0] $end
$var wire 8 ( Q [7:0] $end
$scope module b0 $end
$var wire 1 # clk $end
$var wire 1 ) d $end
$var wire 1 % reset $end
$var reg 1 * q $end
$upscope $end
$scope module b1 $end
$var wire 1 # clk $end
$var wire 1 + d $end
$var wire 1 % reset $end
$var reg 1 , q $end
$upscope $end
$scope module b2 $end
$var wire 1 # clk $end
$var wire 1 - d $end
$var wire 1 % reset $end
$var reg 1 . q $end
$upscope $end
$scope module b3 $end
$var wire 1 # clk $end
$var wire 1 / d $end
$var wire 1 % reset $end
$var reg 1 0 q $end
$upscope $end
$scope module b4 $end
$var wire 1 # clk $end
$var wire 1 1 d $end
$var wire 1 % reset $end
$var reg 1 2 q $end
$upscope $end
$scope module b5 $end
$var wire 1 # clk $end
$var wire 1 3 d $end
$var wire 1 % reset $end
$var reg 1 4 q $end
$upscope $end
$scope module b6 $end
$var wire 1 # clk $end
$var wire 1 5 d $end
$var wire 1 % reset $end
$var reg 1 6 q $end
$upscope $end
$scope module b7 $end
$var wire 1 # clk $end
$var wire 1 7 d $end
$var wire 1 % reset $end
$var reg 1 8 q $end
$upscope $end
$upscope $end
$upscope $end
$enddefinitions $end
$comment Show the parameter values. $end
$dumpall
$end
#0
$dumpvars
x8
x7
x6
x5
x4
x3
x2
x1
x0
x/
x.
x-
x,
x+
x*
x)
bx (
bx '
b0 &
1%
0$
0#
b0 "
bx !
$end
#50
0)
0+
0-
0/
01
03
05
07
b0 '
0*
0,
0.
00
02
04
06
b0 !
b0 (
08
1#
#100
1)
1+
1-
1/
17
b10001111 '
0#
1$
b10001111 "
b10001111 &
0%
#150
18
10
1.
1,
b10001111 !
b10001111 (
1*
1#
#200
0#
b11110000 "
b11110000 &
0$
#250
1#
#300
0)
0+
0-
0/
11
13
15
b11110000 '
0#
1$
#350
16
14
12
00
0.
0,
b11110000 !
b11110000 (
0*
1#
#400
0#
1%
#450
02
04
06
b0 !
b0 (
08
1#
#500
01
03
05
07
b0 '
0#
b10101010 "
b10101010 &
0$
0%
